ivcensor/__init__.py
ivcensor/demo.py
ivcensor/dnn.py
ivcensor/func.py
ivcensor/genius_censor.py
ivcensor-0.4.0.dist-info/METADATA
ivcensor-0.4.0.dist-info/WHEEL
ivcensor-0.4.0.dist-info/top_level.txt
ivcensor-0.4.0.dist-info/RECORD
