Metadata-Version: 2.4
Name: ivcensor
Version: 0.4.0
Summary: IV with right censor data
Author-email: Qiushi Bu <buqiushi17@mails.ucas.ac.cn>
License: MIT
Keywords: right censor data,neural network,instrumental variable,generalized emperical likelihood
Requires-Python: >=3.8
Requires-Dist: numpy>=1.19
Requires-Dist: torch>=1.8
Requires-Dist: scipy>=1.5
Requires-Dist: scikit-learn>=0.24
Requires-Dist: xgboost>=1.3
Requires-Dist: numba>=0.53
